{
  "name": "Helen Willis",
  "age": 65,
  "address": {
    "street": "Ujoipi Junction",
    "city": "Japoezo",
    "state": "NC",
    "zip": "36264"
  },
  "contact": {
    "phone": "(765) 787-4407",
    "servicePhone": "800268159"
  },
  "birthday": "1997-03-02T12:45:13.805Z",
  "ip": "219.221.136.132",
  "foo": "bar",
  "profile": {
    "about": "Wizgabafi ejsi geho kekavot cacahe tackugna louse diljul la tus ipamopupo dusjo us wu vanaj. Pofoj absew mim ohiputid taggepib tukzabasu tuj litvorde fogmega ca umukadod feapo alwam ruwze huf. Nigpegvot vativsu to kahugum noc jov hoobo uk gupocir dus wekon guj vomum folbir diz desivu fevubco boidetif. Lo nahip cebohci zu ranali nirfahup makhiroj vogmi ketupro siz guwilu lojsa egiatumir. Mimu vazzojgi wokjot dod vamlo hulpoba gam zegov dusoofu ned ukabsaj gezetta livitofe nehu orbi.",
    "bio": "Lorde an to aceromvuw zet ge etbaz uvsefge gowo kulufzo eki zoeb jauja or atho lojsi. Dozon muvwuf fom hicas noiguzu bocarvam ikogum jato ke nizcopiw tukekog egekuscas voafimo nujiw ug. Ocu mavducdup utra weos pablod zitan gavroiv ebi udtubu uniwe rut zoin ki lel. Ce bepilus wu befebfas wep carijun pufer mewimew ovpaaz cujwo gavkajol le huvkigud ukaafral ah in sepsigfuh ku. Wan vitel atfi cec uhsad le pome levi aredu mawumfov cuv junov biphug kes feizuuse. Miijojes anelioca sifin behkab se jap rorsu jew cuufiwa tuz imoved wasuwput jap pockica veboz goz nenu pufahol."
  },
  "apiKey": "0d5ac8d6c62e7243b7cadf5c7965ff42c304af4affa5e707a8323a6d8967516a",
  "currency": {
    "code": "USD",
    "name": "United States Dollar"
  }
}