{
  "name": "Emma Price",
  "age": 37,
  "address": {
    "street": "Ewta Avenue",
    "city": "Fubaoho",
    "state": "DC",
    "zip": "92018"
  },
  "contact": {
    "phone": "(311) 443-5492",
    "servicePhone": "800397621"
  },
  "birthday": "1982-09-07T11:24:52.140Z",
  "ip": "159.179.197.36",
  "foo": "bar",
  "profile": {
    "about": "Pijpuv ijehof nojtu jo iciro fojompud teutiho usleh jom micno pomfezev feod viofurop. Zek iwewoga ar mokhe con wu iwizov puhtim cakavjir tul uz jatug. Gule zenwa jo nu ibfu wu vep sihheb evenaco sinuz ripsik muwuet hew zelenit hecjapur jaftu. Gecibuw lupeug kawve ocno labvukrec tapbiefu pif lib hofophe zeb hocigaowo igadatite tidjilri gajenci goik. Lahnelul poub jawoh higa vat ge zuglo zavij susiv ra posu tefehuz dome oc eb.",
    "bio": "Hituc maufaoku cekidmac vale iriabcaz ceksecu hademo nezigu lewzavpe cunpe ven imze haah duret. Owacuvji fekhu lal ewuhuk wumjik bulavu jijhaco ese dujicvez bahut pooda ti erusezto fisboca lakbenke. Wobfecu zazvo hun uwuvug ragehob ti duriv vovop mo vipurjeb lasim pidjamuc ima."
  },
  "apiKey": "e84380d6b15dec8e7ff565e6019ae92ed63be9d7958805599046b5828190bb39",
  "currency": {
    "code": "SBD",
    "name": "Solomon Islands Dollar"
  }
}